WAViMedEEG/ML.py
WAViMedEEG/Prep.py
WAViMedEEG/Standard.py
WAViMedEEG/__init__.py
WAViMedEEG/config.py
WAViMedEEG/template-config.py
WAViMedEEG/tests/__init__.py
wavimedical/ML.py
wavimedical/Prep.py
wavimedical/Standard.py
wavimedical/__init__.py
wavimedical/config.py
wavimedical/template-config.py
wavimedical/tests/__init__.py
wavimedical-0.0.3.dist-info/LICENSE
wavimedical-0.0.3.dist-info/METADATA
wavimedical-0.0.3.dist-info/WHEEL
wavimedical-0.0.3.dist-info/top_level.txt
wavimedical-0.0.3.dist-info/RECORD
