Metadata-Version: 2.1
Name: wavimedical
Version: 0.0.3
Summary: WAVi Medical's EEG Analysis and ML Package
Home-page: https://github.com/canlab/WAViMedEEG
Author: Clayton Schneider
Author-email: clayton.schneider@colorado.edu
License: UNKNOWN
Platform: UNKNOWN
Classifier: Programming Language :: Python :: 3
Classifier: License :: OSI Approved :: MIT License
Classifier: Operating System :: OS Independent
Requires-Python: >=3.8.2
